who_added_this_tag/__init__.py
who_added_this_tag/lorem_ipsum.py
who_added_this_tag/statistics.py
who_added_this_tag/who_added_this_tag.py
who_added_this_tag-0.0.1.dist-info/COPYING
who_added_this_tag-0.0.1.dist-info/METADATA
who_added_this_tag-0.0.1.dist-info/WHEEL
who_added_this_tag-0.0.1.dist-info/top_level.txt
who_added_this_tag-0.0.1.dist-info/RECORD
