Metadata-Version: 2.1
Name: who-added-this-tag
Version: 0.0.1
Summary: A tool to research who added given OSM tags currently in use
Home-page: https://codeberg.org/matkoniecz/who-added-this-tag
Author: Mateusz Konieczny
Author-email: matkoniecz@tutanota.com
License: UNKNOWN
Platform: UNKNOWN
Classifier: Programming Language :: Python :: 3
Classifier: Operating System :: OS Independent
